gxkit_dbtools/__init__.py
gxkit_dbtools/exception.py
gxkit_dbtools/py.typed
gxkit_dbtools/client/__init__.py
gxkit_dbtools/client/base.py
gxkit_dbtools/client/clickhouse_client.py
gxkit_dbtools/client/iotdb_client.py
gxkit_dbtools/client/mysql_client.py
gxkit_dbtools/client/utils.py
gxkit_dbtools/parser/__init__.py
gxkit_dbtools/parser/sql_parser.py
gxkit_dbtools/parser/utils.py
gxkit_dbtools-0.1.2.post6.dist-info/licenses/LICENSE
gxkit_dbtools-0.1.2.post6.dist-info/METADATA
gxkit_dbtools-0.1.2.post6.dist-info/WHEEL
gxkit_dbtools-0.1.2.post6.dist-info/top_level.txt
gxkit_dbtools-0.1.2.post6.dist-info/RECORD
