Metadata-Version: 2.4
Name: gxkit-dbtools
Version: 0.1.2.post6
Summary: Gx Company Development Toolkit - DBTools Module
Author-email: Shaojiayi <shaojy@sunburst.com.cn>
License: Apache-2.0
Requires-Python: >=3.8
License-File: LICENSE
Requires-Dist: pymysql
Requires-Dist: clickhouse-driver
Requires-Dist: apache-iotdb
Requires-Dist: cryptography
Requires-Dist: sqlglot
Requires-Dist: zstd
Dynamic: license-file
